infi.logging-0.4.9-py2.7-nspkg.pth
infi/logging/__init__.py
infi/logging/__version__.py
infi/logging/compat.py
infi/logging/eventlog_amd64.dll
infi/logging/eventlog_x86.dll
infi/logging/formatters.py
infi/logging/globals.py
infi/logging/processors.py
infi/logging/slow_greenlets.py
infi/logging/timing.py
infi/logging/win32.py
infi/logging/wrappers.py
infi/logging/handlers/__init__.py
infi/logging/handlers/rotating_file_handler.py
infi/logging/handlers/syslog_handler.py
infi/logging/plugins/__init__.py
infi/logging/plugins/channel.py
infi/logging/plugins/greenlet_id.py
infi/logging/plugins/hostname.py
infi/logging/plugins/log_level.py
infi/logging/plugins/message.py
infi/logging/plugins/process_id.py
infi/logging/plugins/procname.py
infi/logging/plugins/request_id_tag.py
infi/logging/plugins/thread_id.py
infi/logging/plugins/time.py
infi.logging-0.4.9.dist-info/LICENSE
infi.logging-0.4.9.dist-info/METADATA
infi.logging-0.4.9.dist-info/WHEEL
infi.logging-0.4.9.dist-info/entry_points.txt
infi.logging-0.4.9.dist-info/namespace_packages.txt
infi.logging-0.4.9.dist-info/top_level.txt
infi.logging-0.4.9.dist-info/RECORD
