Metadata-Version: 2.1
Name: infi.logging
Version: 0.4.9
Summary: Extensions for logbook, such as Windows EventLog handler.
Home-page: https://github.com/Infinidat/infi.logging
Author: Arnon Yaari
Author-email: arnony@infinidat.com
License: BSD
Platform: UNKNOWN
Classifier: Intended Audience :: Developers
Classifier: Intended Audience :: System Administrators
Classifier: License :: OSI Approved :: BSD License
Classifier: Operating System :: OS Independent
Classifier: Programming Language :: Python
Classifier: Programming Language :: Python :: 2
Classifier: Programming Language :: Python :: 3
Classifier: Topic :: Software Development :: Libraries :: Python Modules
Requires-Dist: infi.registry
Requires-Dist: Logbook
Requires-Dist: setuptools
Requires-Dist: six
